{
  "xBRIEFInfo": {
    "version": "0.6",
    "author": "agent:deft-directive-setup",
    "description": "Scope xBRIEF",
    "created": "2026-07-04T21:05:00Z"
  },
  "plan": {
    "title": "Break prompts",
    "status": "proposed",
    "narratives": {
      "Overview": "Configurable prompts to stretch, walk, and drink water: a gentle audio cue through the already-playing stream, an in-app banner, and optional browser notifications.",
      "Requirements": "FR-1: Configurable break types (stretch, walk, water, custom label) each with its own interval and enable toggle. FR-2: Audio cue plays through the master bus when a break fires. FR-3: Optional Notification API alerts with graceful degradation when permission is denied. FR-4: In-app banner with dismiss and snooze. NFR-1: Prompts fire reliably while the tab is backgrounded (audio-clock-driven, not setTimeout-only)."
    },
    "items": [
      {
        "title": "Break schedule model and per-type configuration UI",
        "status": "pending",
        "narrative": {
          "Traces": "FR-1"
        }
      },
      {
        "title": "Audio cue + in-app banner with snooze/dismiss",
        "status": "pending",
        "narrative": {
          "Traces": "FR-2, FR-4, NFR-1"
        }
      },
      {
        "title": "Browser notifications with permission fallback",
        "status": "pending",
        "narrative": {
          "Traces": "FR-3"
        }
      }
    ]
  }
}
